django_rpyc/__init__.py
django_rpyc/apps.py
django_rpyc/decorators.py
django_rpyc/server.py
django_rpyc/management/commands/__init__.py
django_rpyc/management/commands/run_rpyc.py
django_rpyc/management/commands/__pycache__/__init__.cpython-312.pyc
django_rpyc/management/commands/__pycache__/run_rpyc.cpython-312.pyc
django_rpyc/migrations/__init__.py
django_rpyc-0.1.13.dist-info/LICENSE
django_rpyc-0.1.13.dist-info/METADATA
django_rpyc-0.1.13.dist-info/WHEEL
django_rpyc-0.1.13.dist-info/top_level.txt
django_rpyc-0.1.13.dist-info/RECORD
